<annotation>
	<folder>CS dataset</folder>
	<filename>scene03976.jpeg</filename>
	<path>E:\machine learning\CS DATA\CS dataset\scene03976.jpeg</path>
	<source>
		<database>Unknown</database>
	</source>
	<size>
		<width>1280</width>
		<height>800</height>
		<depth>3</depth>
	</size>
	<segmented>0</segmented>
	<object>
		<name>terr2</name>
		<pose>Unspecified</pose>
		<truncated>0</truncated>
		<difficult>0</difficult>
		<bndbox>
			<xmin>1046</xmin>
			<ymin>146</ymin>
			<xmax>1176</xmax>
			<ymax>337</ymax>
		</bndbox>
	</object>
</annotation>
